{
  "project_info": {
    "project_number": "488711773154",
    "project_id": "visionassistant-17f8c",
    "storage_bucket": "visionassistant-17f8c.appspot.com"
  },
  "client": [
    {
      "client_info": {
        "mobilesdk_app_id": "1:488711773154:android:34d757696c965d1291f7bb",
        "android_client_info": {
          "package_name": "com.app.miniproject.iiita.visionassistant"
        }
      },
      "oauth_client": [
        {
          "client_id": "488711773154-l29jkntgrfk0imq9hpbg6cpn2dss9q42.apps.googleusercontent.com",
          "client_type": 3
        }
      ],
      "api_key": [
        {
          "current_key": "AIzaSyBzV3QX-W4vNVo2oZpi0-fpB3K6eVlBqfE"
        }
      ],
      "services": {
        "appinvite_service": {
          "other_platform_oauth_client": [
            {
              "client_id": "488711773154-l29jkntgrfk0imq9hpbg6cpn2dss9q42.apps.googleusercontent.com",
              "client_type": 3
            }
          ]
        }
      }
    },
    {
      "client_info": {
        "mobilesdk_app_id": "1:488711773154:android:ebebf753cfeb51d791f7bb",
        "android_client_info": {
          "package_name": "com.app.visionassistant"
        }
      },
      "oauth_client": [
        {
          "client_id": "488711773154-5b5nnp2aef8pk2033ur4o9ggef91umo3.apps.googleusercontent.com",
          "client_type": 1,
          "android_info": {
            "package_name": "com.app.visionassistant",
            "certificate_hash": "7f9904a04da32a0cf56d0d155c66c8093c0b2f24"
          }
        },
        {
          "client_id": "488711773154-p058g6obuj85tqbpq3o8j7a8s88g8fbm.apps.googleusercontent.com",
          "client_type": 1,
          "android_info": {
            "package_name": "com.app.visionassistant",
            "certificate_hash": "13ee37f7128aded4f7974d8f550500f965204dc4"
          }
        },
        {
          "client_id": "488711773154-l29jkntgrfk0imq9hpbg6cpn2dss9q42.apps.googleusercontent.com",
          "client_type": 3
        }
      ],
      "api_key": [
        {
          "current_key": "AIzaSyBzV3QX-W4vNVo2oZpi0-fpB3K6eVlBqfE"
        }
      ],
      "services": {
        "appinvite_service": {
          "other_platform_oauth_client": [
            {
              "client_id": "488711773154-l29jkntgrfk0imq9hpbg6cpn2dss9q42.apps.googleusercontent.com",
              "client_type": 3
            }
          ]
        }
      }
    }
  ],
  "configuration_version": "1"
}